LICENSE
README.rst
setup.py
sqlalchemy_dm/__init__.py
sqlalchemy_dm/base.py
sqlalchemy_dm/dmPython.py
sqlalchemy_dm/types.py
sqlalchemy_dm_deepfos.egg-info/PKG-INFO
sqlalchemy_dm_deepfos.egg-info/SOURCES.txt
sqlalchemy_dm_deepfos.egg-info/dependency_links.txt
sqlalchemy_dm_deepfos.egg-info/entry_points.txt
sqlalchemy_dm_deepfos.egg-info/requires.txt
sqlalchemy_dm_deepfos.egg-info/top_level.txt