Metadata-Version: 1.0
Name: sqlalchemy-dm-deepfos
Version: 2.0.1
Summary: SQLAlchemy dialect for DM
Home-page: UNKNOWN
Author: Dameng
Author-email: UNKNOWN
License: UNKNOWN
Keywords: DM SQLAlchemy
Platform: UNKNOWN
